azure/mgmt/loganalytics/__init__.py
azure/mgmt/loganalytics/_configuration.py
azure/mgmt/loganalytics/_log_analytics_management_client.py
azure/mgmt/loganalytics/_patch.py
azure/mgmt/loganalytics/_version.py
azure/mgmt/loganalytics/py.typed
azure/mgmt/loganalytics/_utils/__init__.py
azure/mgmt/loganalytics/_utils/serialization.py
azure/mgmt/loganalytics/aio/__init__.py
azure/mgmt/loganalytics/aio/_configuration.py
azure/mgmt/loganalytics/aio/_log_analytics_management_client.py
azure/mgmt/loganalytics/aio/_patch.py
azure/mgmt/loganalytics/aio/operations/__init__.py
azure/mgmt/loganalytics/aio/operations/_available_service_tiers_operations.py
azure/mgmt/loganalytics/aio/operations/_clusters_operations.py
azure/mgmt/loganalytics/aio/operations/_data_exports_operations.py
azure/mgmt/loganalytics/aio/operations/_data_sources_operations.py
azure/mgmt/loganalytics/aio/operations/_deleted_workspaces_operations.py
azure/mgmt/loganalytics/aio/operations/_gateways_operations.py
azure/mgmt/loganalytics/aio/operations/_intelligence_packs_operations.py
azure/mgmt/loganalytics/aio/operations/_linked_services_operations.py
azure/mgmt/loganalytics/aio/operations/_linked_storage_accounts_operations.py
azure/mgmt/loganalytics/aio/operations/_management_groups_operations.py
azure/mgmt/loganalytics/aio/operations/_operation_statuses_operations.py
azure/mgmt/loganalytics/aio/operations/_operations.py
azure/mgmt/loganalytics/aio/operations/_patch.py
azure/mgmt/loganalytics/aio/operations/_queries_operations.py
azure/mgmt/loganalytics/aio/operations/_query_packs_operations.py
azure/mgmt/loganalytics/aio/operations/_saved_searches_operations.py
azure/mgmt/loganalytics/aio/operations/_schema_operations.py
azure/mgmt/loganalytics/aio/operations/_shared_keys_operations.py
azure/mgmt/loganalytics/aio/operations/_storage_insight_configs_operations.py
azure/mgmt/loganalytics/aio/operations/_summary_logs_operations.py
azure/mgmt/loganalytics/aio/operations/_tables_operations.py
azure_mgmt_loganalytics-13.1.0.dist-info/licenses/LICENSE
azure_mgmt_loganalytics-13.1.0.dist-info/METADATA
azure_mgmt_loganalytics-13.1.0.dist-info/WHEEL
azure_mgmt_loganalytics-13.1.0.dist-info/top_level.txt
azure_mgmt_loganalytics-13.1.0.dist-info/RECORD
